[{
  "adult": false,
  "backdrop_path": "/2yDV0xLyqW88dn5qE7YCRnoYmfy.jpg",
  "created_by": [],
  "episode_run_time": [
    60
  ],
  "first_air_date": "2001-09-09",
  "genres": [{
      "id": 18,
      "name": "Drama"
    },
    {
      "id": 10768,
      "name": "War & Politics"
    }
  ],
  "homepage": "http://www.hbo.com/band-of-brothers",
  "id": 4613,
  "in_production": false,
  "languages": [
    "de",
    "fr",
    "lt",
    "nl",
    "en"
  ],
  "last_air_date": "2001-11-04",
  "last_episode_to_air": {
    "id": 334396,
    "name": "Points",
    "overview": "As the Germans surrender, it appears that that the hard days for Easy Company are over as they are stationed in Austria. But they soon learn that those solders without enough service points will be sent to fight in Japan.",
    "vote_average": 8.5,
    "vote_count": 53,
    "air_date": "2001-11-04",
    "episode_number": 10,
    "production_code": "110",
    "runtime": 62,
    "season_number": 1,
    "show_id": 4613,
    "still_path": "/tJCNQhY3fHn1OIwImfZQUIRPbuA.jpg"
  },
  "name": "Band of Brothers",
  "next_episode_to_air": null,
  "networks": [{
    "id": 49,
    "logo_path": "/tuomPhY2UtuPTqqFnKMVHvSb724.png",
    "name": "HBO",
    "origin_country": "US"
  }],
  "number_of_episodes": 10,
  "number_of_seasons": 1,
  "origin_country": [
    "US"
  ],
  "original_language": "en",
  "original_name": "Band of Brothers",
  "overview": "Drawn from interviews with survivors of Easy Company, as well as their journals and letters, Band of Brothers chronicles the experiences of these men from paratrooper training in Georgia through the end of the war. As an elite rifle company parachuting into Normandy early on D-Day morning, participants in the Battle of the Bulge, and witness to the horrors of war, the men of Easy knew extraordinary bravery and extraordinary fear - and became the stuff of legend. Based on Stephen E. Ambrose's acclaimed book of the same name.",
  "popularity": 65.851,
  "poster_path": "/uC128zXoZ1MvtsxWbAu11qHcMi2.jpg",
  "production_companies": [{
      "id": 7429,
      "logo_path": "/6in9uMqxXEHx5XgYgkeRBpZ4rPw.png",
      "name": "HBO Films",
      "origin_country": "US"
    },
    {
      "id": 15258,
      "logo_path": "/d6Aqo5YatP3SUkMi1PEwT0nK0GB.png",
      "name": "DreamWorks Television",
      "origin_country": "US"
    },
    {
      "id": 7,
      "logo_path": "/vru2SssLX3FPhnKZGtYw00pVIS9.png",
      "name": "DreamWorks Pictures",
      "origin_country": "US"
    },
    {
      "id": 110808,
      "logo_path": null,
      "name": "BBC Television Centre",
      "origin_country": "GB"
    },
    {
      "id": 4171,
      "logo_path": "/ip8rzankhLLhJGGkvfCirfUM26d.png",
      "name": "Playtone",
      "origin_country": "US"
    }
  ],
  "production_countries": [{
      "iso_3166_1": "CH",
      "name": "Switzerland"
    },
    {
      "iso_3166_1": "GB",
      "name": "United Kingdom"
    },
    {
      "iso_3166_1": "US",
      "name": "United States of America"
    }
  ],
  "seasons": [{
      "air_date": "2001-11-10",
      "episode_count": 5,
      "id": 14071,
      "name": "Specials",
      "overview": "",
      "poster_path": "/h3QMxv1JYozrFQCbPNxnP7x7F6b.jpg",
      "season_number": 0
    },
    {
      "air_date": "2001-09-09",
      "episode_count": 10,
      "id": 14070,
      "name": "Miniseries",
      "overview": "",
      "poster_path": "/1dTx3cRcSpaOCe0mXOVEBjz25z3.jpg",
      "season_number": 1
    }
  ],
  "spoken_languages": [{
      "english_name": "German",
      "iso_639_1": "de",
      "name": "Deutsch"
    },
    {
      "english_name": "French",
      "iso_639_1": "fr",
      "name": "Français"
    },
    {
      "english_name": "Lithuanian",
      "iso_639_1": "lt",
      "name": "Lietuvių"
    },
    {
      "english_name": "Dutch",
      "iso_639_1": "nl",
      "name": "Nederlands"
    },
    {
      "english_name": "English",
      "iso_639_1": "en",
      "name": "English"
    }
  ],
  "status": "Ended",
  "tagline": "There was a time when the world asked ordinary men to do extraordinary things.",
  "type": "Miniseries",
  "vote_average": 8.5,
  "vote_count": 3017
}, {
  "adult": false,
  "backdrop_path": "/l0qVZIpXtIo7km9u5Yqh0nKPOr5.jpg",
  "created_by": [{
      "id": 163461,
      "credit_id": "525710bf19c295731c03280b",
      "name": "Marta Kauffman",
      "gender": 1,
      "profile_path": "/AsX4ZOoQP5oQVLiA51zdRiTNKTm.jpg"
    },
    {
      "id": 1216352,
      "credit_id": "525710bf19c295731c032811",
      "name": "David Crane",
      "gender": 2,
      "profile_path": "/1NYo5ZYCSqoxQ5sqXLMDm3cqvKp.jpg"
    }
  ],
  "episode_run_time": [
    25
  ],
  "first_air_date": "1994-09-22",
  "genres": [{
      "id": 35,
      "name": "Comedy"
    },
    {
      "id": 18,
      "name": "Drama"
    }
  ],
  "homepage": "https://www.netflix.com/title/70153404",
  "id": 1668,
  "in_production": false,
  "languages": [
    "en"
  ],
  "last_air_date": "2004-05-06",
  "last_episode_to_air": {
    "id": 87632,
    "name": "The Last One",
    "overview": "Ross and Phoebe chase Rachel to the airport, but end up at the wrong one. Chandler and Monica finish packing for their move to the suburbs, and Joey loses Chick Jr. and Duck Jr. in the foosball table.\n\nThe series finale finds Rachel, Monica, Phoebe, Joey, Chandler and Ross embarking on the next chapters in their lives. The six of them have been there for one another through all the ups and downs of becoming adults. Now it's their last day together, and it's one of momentous events and last-minute surprises. Even as the friends make major decisions, they share a bond that will last forever.",
    "vote_average": 9.4,
    "vote_count": 29,
    "air_date": "2004-05-06",
    "episode_number": 17,
    "production_code": "176266 / 176267",
    "runtime": 48,
    "season_number": 10,
    "show_id": 1668,
    "still_path": "/7XmwmXkJtObpt6ABPENanrJHlg9.jpg"
  },
  "name": "Friends",
  "next_episode_to_air": null,
  "networks": [{
    "id": 6,
    "logo_path": "/cm111bsDVlYaC1foL0itvEI4yLG.png",
    "name": "NBC",
    "origin_country": "US"
  }],
  "number_of_episodes": 228,
  "number_of_seasons": 10,
  "origin_country": [
    "US"
  ],
  "original_language": "en",
  "original_name": "Friends",
  "overview": "Six young people from New York City, on their own and struggling to survive in the real world, find the companionship, comfort and support they get from each other to be the perfect antidote to the pressures of life.",
  "popularity": 253.906,
  "poster_path": "/f496cm9enuEsZkSPzCwnTESEK5s.jpg",
  "production_companies": [{
      "id": 1957,
      "logo_path": "/pJJw98MtNFC9cHn3o15G7vaUnnX.png",
      "name": "Warner Bros. Television",
      "origin_country": "US"
    },
    {
      "id": 31810,
      "logo_path": "/3oyBCnFO3tIRmny3yzYQpF5n2cS.png",
      "name": "Bright/Kauffman/Crane Productions",
      "origin_country": "US"
    }
  ],
  "production_countries": [{
    "iso_3166_1": "US",
    "name": "United States of America"
  }],
  "seasons": [{
      "air_date": "2001-02-14",
      "episode_count": 39,
      "id": 4583,
      "name": "Specials",
      "overview": "",
      "poster_path": "/xaEj0Vw0LOmp7kBeX2vmYPb5sTg.jpg",
      "season_number": 0
    },
    {
      "air_date": "1994-09-22",
      "episode_count": 24,
      "id": 4573,
      "name": "Season 1",
      "overview": "",
      "poster_path": "/odCW88Cq5hAF0ZFVOkeJmeQv1nV.jpg",
      "season_number": 1
    },
    {
      "air_date": "1995-09-21",
      "episode_count": 24,
      "id": 4574,
      "name": "Season 2",
      "overview": "",
      "poster_path": "/kC9VHoMh1KkoAYfsY3QlHpZRxDy.jpg",
      "season_number": 2
    },
    {
      "air_date": "1996-09-16",
      "episode_count": 25,
      "id": 4575,
      "name": "Season 3",
      "overview": "",
      "poster_path": "/n9u4pslqb6tpiLc8soldL5IbAyG.jpg",
      "season_number": 3
    },
    {
      "air_date": "1997-09-25",
      "episode_count": 23,
      "id": 4576,
      "name": "Season 4",
      "overview": "",
      "poster_path": "/3WdH3FNMXgp3Qlx21T7kwKS8Mtc.jpg",
      "season_number": 4
    },
    {
      "air_date": "1998-09-24",
      "episode_count": 23,
      "id": 4577,
      "name": "Season 5",
      "overview": "",
      "poster_path": "/aEwLXWbo6gV1TNIv9veu4rRwsPZ.jpg",
      "season_number": 5
    },
    {
      "air_date": "1999-09-23",
      "episode_count": 23,
      "id": 4578,
      "name": "Season 6",
      "overview": "",
      "poster_path": "/7EU6bV6d8j1Xbc1F8QoNkOZrpsi.jpg",
      "season_number": 6
    },
    {
      "air_date": "2000-10-12",
      "episode_count": 23,
      "id": 4579,
      "name": "Season 7",
      "overview": "",
      "poster_path": "/yvUZVChjOnqCjB9rjdEqEmpDdnQ.jpg",
      "season_number": 7
    },
    {
      "air_date": "2001-09-27",
      "episode_count": 23,
      "id": 4580,
      "name": "Season 8",
      "overview": "",
      "poster_path": "/eh6PPkrzkXsEksRJDcdtx9lZsqX.jpg",
      "season_number": 8
    },
    {
      "air_date": "2002-09-26",
      "episode_count": 23,
      "id": 4581,
      "name": "Season 9",
      "overview": "",
      "poster_path": "/1IvIdN4I5jJ0bwC3BkmDCy4pQ9j.jpg",
      "season_number": 9
    },
    {
      "air_date": "2003-09-25",
      "episode_count": 17,
      "id": 4582,
      "name": "Season 10",
      "overview": "",
      "poster_path": "/67ETB6XIqYc5vZkyAjN8XINOX5i.jpg",
      "season_number": 10
    }
  ],
  "spoken_languages": [{
    "english_name": "English",
    "iso_639_1": "en",
    "name": "English"
  }],
  "status": "Ended",
  "tagline": "I'll be there for you",
  "type": "Scripted",
  "vote_average": 8.447,
  "vote_count": 6952,
  "credits": {
    "cast": [{
        "adult": false,
        "gender": 1,
        "id": 4491,
        "known_for_department": "Acting",
        "name": "Jennifer Aniston",
        "original_name": "Jennifer Aniston",
        "popularity": 35.101,
        "profile_path": "/qPXG41rYdUGldZhMhuZFvmpZKRp.jpg",
        "character": "Rachel Green",
        "credit_id": "525710bd19c295731c03242d",
        "order": 0
      },
      {
        "adult": false,
        "gender": 1,
        "id": 14405,
        "known_for_department": "Acting",
        "name": "Courteney Cox",
        "original_name": "Courteney Cox",
        "popularity": 24.096,
        "profile_path": "/3bTVQH9vBXAiwGVHXKLylStz4RT.jpg",
        "character": "Monica Geller",
        "credit_id": "525710bc19c295731c032341",
        "order": 1
      },
      {
        "adult": false,
        "gender": 1,
        "id": 14406,
        "known_for_department": "Acting",
        "name": "Lisa Kudrow",
        "original_name": "Lisa Kudrow",
        "popularity": 20.744,
        "profile_path": "/9YNzHuT7L0wdEl3zua6iUYz5tYT.jpg",
        "character": "Phoebe Buffay",
        "credit_id": "525710bd19c295731c032525",
        "order": 2
      },
      {
        "adult": false,
        "gender": 2,
        "id": 14407,
        "known_for_department": "Acting",
        "name": "Matt LeBlanc",
        "original_name": "Matt LeBlanc",
        "popularity": 7.797,
        "profile_path": "/a7Fl1sLUq1UDJ4pHsnwpBdEiDEZ.jpg",
        "character": "Joey Tribbiani",
        "credit_id": "525710bd19c295731c0323a3",
        "order": 3
      },
      {
        "adult": false,
        "gender": 2,
        "id": 14408,
        "known_for_department": "Acting",
        "name": "Matthew Perry",
        "original_name": "Matthew Perry",
        "popularity": 16.337,
        "profile_path": "/ecDzkLWPV1z0x31I1GTjNmLxAHk.jpg",
        "character": "Chandler Bing",
        "credit_id": "525710be19c295731c03256f",
        "order": 4
      },
      {
        "adult": false,
        "gender": 2,
        "id": 14409,
        "known_for_department": "Acting",
        "name": "David Schwimmer",
        "original_name": "David Schwimmer",
        "popularity": 16.535,
        "profile_path": "/oBsK1ql5bo3zxepbQCclIwnapXM.jpg",
        "character": "Ross Geller",
        "credit_id": "525710bd19c295731c0324a9",
        "order": 5
      }
    ],
    "crew": [{
        "adult": false,
        "gender": 0,
        "id": 1226573,
        "known_for_department": "Production",
        "name": "Richard Choi",
        "original_name": "Richard Choi",
        "popularity": 0.6,
        "profile_path": null,
        "credit_id": "525710d619c295731c03306f",
        "department": "Production",
        "job": "Producer"
      },
      {
        "adult": false,
        "gender": 2,
        "id": 1224760,
        "known_for_department": "Writing",
        "name": "Robert Carlock",
        "original_name": "Robert Carlock",
        "popularity": 2.076,
        "profile_path": null,
        "credit_id": "525710d419c295731c033031",
        "department": "Production",
        "job": "Producer"
      },
      {
        "adult": false,
        "gender": 2,
        "id": 1226552,
        "known_for_department": "Writing",
        "name": "Mark Kunerth",
        "original_name": "Mark Kunerth",
        "popularity": 0.6,
        "profile_path": null,
        "credit_id": "525710c719c295731c032b5b",
        "department": "Production",
        "job": "Producer"
      },
      {
        "adult": false,
        "gender": 1,
        "id": 1226555,
        "known_for_department": "Creator",
        "name": "Dana Klein",
        "original_name": "Dana Klein",
        "popularity": 0.6,
        "profile_path": null,
        "credit_id": "525710c919c295731c032c7f",
        "department": "Production",
        "job": "Producer"
      },
      {
        "adult": false,
        "gender": 2,
        "id": 1226460,
        "known_for_department": "Writing",
        "name": "Sebastian Jones",
        "original_name": "Sebastian Jones",
        "popularity": 0.6,
        "profile_path": null,
        "credit_id": "525710d119c295731c032f67",
        "department": "Production",
        "job": "Producer"
      },
      {
        "adult": false,
        "gender": 2,
        "id": 1215784,
        "known_for_department": "Writing",
        "name": "Brian Buckner",
        "original_name": "Brian Buckner",
        "popularity": 0.6,
        "profile_path": null,
        "credit_id": "525710d119c295731c032f27",
        "department": "Production",
        "job": "Producer"
      },
      {
        "adult": false,
        "gender": 1,
        "id": 1226564,
        "known_for_department": "Writing",
        "name": "Ellen Plummer",
        "original_name": "Ellen Plummer",
        "popularity": 0.6,
        "profile_path": null,
        "credit_id": "525710cf19c295731c032e9b",
        "department": "Production",
        "job": "Producer"
      },
      {
        "adult": false,
        "gender": 0,
        "id": 193707,
        "known_for_department": "Writing",
        "name": "Sherry Bilsing",
        "original_name": "Sherry Bilsing",
        "popularity": 0.644,
        "profile_path": null,
        "credit_id": "525710c419c295731c0329bb",
        "department": "Production",
        "job": "Producer"
      },
      {
        "adult": false,
        "gender": 2,
        "id": 1215936,
        "known_for_department": "Writing",
        "name": "Ted Cohen",
        "original_name": "Ted Cohen",
        "popularity": 1.62,
        "profile_path": null,
        "credit_id": "525710c319c295731c032977",
        "department": "Production",
        "job": "Producer"
      },
      {
        "adult": false,
        "gender": 2,
        "id": 1217286,
        "known_for_department": "Writing",
        "name": "Scott Silveri",
        "original_name": "Scott Silveri",
        "popularity": 0.84,
        "profile_path": null,
        "credit_id": "525710c519c295731c032a89",
        "department": "Production",
        "job": "Producer"
      },
      {
        "adult": false,
        "gender": 1,
        "id": 1217284,
        "known_for_department": "Writing",
        "name": "Shana Goldberg-Meehan",
        "original_name": "Shana Goldberg-Meehan",
        "popularity": 0.6,
        "profile_path": null,
        "credit_id": "525710c519c295731c032a01",
        "department": "Production",
        "job": "Producer"
      },
      {
        "adult": false,
        "gender": 2,
        "id": 1215935,
        "known_for_department": "Writing",
        "name": "Andrew Reich",
        "original_name": "Andrew Reich",
        "popularity": 0.6,
        "profile_path": null,
        "credit_id": "525710c919c295731c032cc3",
        "department": "Production",
        "job": "Producer"
      },
      {
        "adult": false,
        "gender": 0,
        "id": 1226546,
        "known_for_department": "Production",
        "name": "Todd Stevens",
        "original_name": "Todd Stevens",
        "popularity": 0.6,
        "profile_path": null,
        "credit_id": "525710c319c295731c032933",
        "department": "Production",
        "job": "Producer"
      },
      {
        "adult": false,
        "gender": 0,
        "id": 1226543,
        "known_for_department": "Production",
        "name": "Wendy Knoller",
        "original_name": "Wendy Knoller",
        "popularity": 0.6,
        "profile_path": null,
        "credit_id": "525710c119c295731c0328e3",
        "department": "Production",
        "job": "Producer"
      },
      {
        "adult": false,
        "gender": 1,
        "id": 41084,
        "known_for_department": "Costume & Make-Up",
        "name": "Debra McGuire",
        "original_name": "Debra McGuire",
        "popularity": 1.388,
        "profile_path": "/2wH44GuUhNUORaANbwOjJNmkC3r.jpg",
        "credit_id": "59a72bc7925141579d005073",
        "department": "Costume & Make-Up",
        "job": "Costume Design"
      },
      {
        "adult": false,
        "gender": 0,
        "id": 1332209,
        "known_for_department": "Art",
        "name": "Greg J. Grande",
        "original_name": "Greg J. Grande",
        "popularity": 0.6,
        "profile_path": null,
        "credit_id": "59a72bc09251415808005106",
        "department": "Art",
        "job": "Set Decoration"
      },
      {
        "adult": false,
        "gender": 0,
        "id": 1480314,
        "known_for_department": "Sound",
        "name": "Charlie McDaniel",
        "original_name": "Charlie McDaniel",
        "popularity": 0.6,
        "profile_path": null,
        "credit_id": "5b8d691e0e0a261d6e051a26",
        "department": "Sound",
        "job": "Sound Re-Recording Mixer"
      },
      {
        "adult": false,
        "gender": 0,
        "id": 1638552,
        "known_for_department": "Camera",
        "name": "Kevin McGill",
        "original_name": "Kevin McGill",
        "popularity": 0.6,
        "profile_path": null,
        "credit_id": "5b8d69ad0e0a261d7304d971",
        "department": "Camera",
        "job": "First Assistant Camera"
      },
      {
        "adult": false,
        "gender": 0,
        "id": 1881668,
        "known_for_department": "Sound",
        "name": "John Bickelhaupt",
        "original_name": "John Bickelhaupt",
        "popularity": 0.6,
        "profile_path": null,
        "credit_id": "5b8d68d5c3a368520904ff8d",
        "department": "Sound",
        "job": "Sound Re-Recording Mixer"
      },
      {
        "adult": false,
        "gender": 0,
        "id": 1438574,
        "known_for_department": "Crew",
        "name": "James Fredburg",
        "original_name": "James Fredburg",
        "popularity": 0.6,
        "profile_path": null,
        "credit_id": "5b8d695c9251415183047b7a",
        "department": "Visual Effects",
        "job": "Special Effects Supervisor"
      },
      {
        "adult": false,
        "gender": 2,
        "id": 1218971,
        "known_for_department": "Production",
        "name": "Kevin S. Bright",
        "original_name": "Kevin S. Bright",
        "popularity": 1.166,
        "profile_path": null,
        "credit_id": "525710c719c295731c032ba9",
        "department": "Production",
        "job": "Executive Producer"
      },
      {
        "adult": false,
        "gender": 2,
        "id": 1216352,
        "known_for_department": "Writing",
        "name": "David Crane",
        "original_name": "David Crane",
        "popularity": 2.697,
        "profile_path": "/1NYo5ZYCSqoxQ5sqXLMDm3cqvKp.jpg",
        "credit_id": "60bdc46feb79c20040b0a362",
        "department": "Production",
        "job": "Executive Producer"
      },
      {
        "adult": false,
        "gender": 1,
        "id": 163461,
        "known_for_department": "Writing",
        "name": "Marta Kauffman",
        "original_name": "Marta Kauffman",
        "popularity": 2.024,
        "profile_path": "/AsX4ZOoQP5oQVLiA51zdRiTNKTm.jpg",
        "credit_id": "60bdc4930bc529006f26d3be",
        "department": "Production",
        "job": "Executive Producer"
      }
    ]
  }
}]